detectools/__init__.py
detectools/config/__init__.py
detectools/config/config.py
detectools/config/errors.py
detectools/data/__init__.py
detectools/data/additional_augmentations.py
detectools/data/augmentation_class.py
detectools/data/dataset.py
detectools/data/errors.py
detectools/data/data_reader/__init__.py
detectools/data/data_reader/readers.py
detectools/formats/__init__.py
detectools/formats/base_data.py
detectools/formats/base_formats.py
detectools/formats/errors.py
detectools/formats/formats.py
detectools/formats/utils.py
detectools/inference/__init__.py
detectools/inference/patchifier.py
detectools/inference/predictor.py
detectools/metrics/__init__.py
detectools/metrics/available_metrics.py
detectools/metrics/base_metric.py
detectools/metrics/func.py
detectools/metrics/matcher.py
detectools/metrics/utils.py
detectools/models/__init__.py
detectools/models/basemodel.py
detectools/models/mask2former/__init__.py
detectools/models/mask2former/mask2former.py
detectools/models/yolov8/__init__.py
detectools/models/yolov8/errors.py
detectools/models/yolov8/utils.py
detectools/models/yolov8/yolov8.py
detectools/models/yolov8seg/__init__.py
detectools/models/yolov8seg/errors.py
detectools/models/yolov8seg/utils.py
detectools/models/yolov8seg/yolov8seg.py
detectools/preprocessing/__init__.py
detectools/preprocessing/image.py
detectools/preprocessing/preprocessing.py
detectools/train/__init__.py
detectools/train/trainer.py
detectools/utils/__init__.py
detectools/utils/errors.py
detectools/utils/visualization.py
detectools-1.0.4.dist-info/LICENSE.txt
detectools-1.0.4.dist-info/METADATA
detectools-1.0.4.dist-info/WHEEL
detectools-1.0.4.dist-info/top_level.txt
detectools-1.0.4.dist-info/RECORD
