Metadata-Version: 2.1
Name: detectools
Version: 1.0.4
Summary: Overlay of PyTorch to generalize trainning and inference processes for detection & instance segmentation tasks.
Author-email: Lucas Bernigaud Samatan <lucas.bernigaud-samatan@inrae.fr>, Jordan Bernigaud Samatan <jordan.bernigaud-samatan@inrae.fr>
Maintainer-email: Jordan Bernigaud Samatan <jordan.bernigaud-samatan@inrae.fr>
License: GNU Affero General Public License v3 or later (AGPLv3+) (AGPL-3.0).
Project-URL: Homepage, https://forgemia.inra.fr/ue-apc/librairies/python/detectools_v1
Project-URL: Issues, https://forgemia.inra.fr/ue-apc/librairies/python/detectools_v1/-/issues
Project-URL: Documentation, https://detectools.readthedocs.io/en/latest/
Project-URL: Repository, https://forgemia.inra.fr/ue-apc/librairies/python/detectools_v1
Classifier: Development Status :: 3 - Alpha
Classifier: Programming Language :: Python :: 3.11
Requires-Python: >=3.11.9
License-File: LICENSE.txt
Requires-Dist: torch==2.4.0
Requires-Dist: torchvision==0.19.0
Requires-Dist: pycocotools==2.0.8
Requires-Dist: torchmetrics==1.4.0
Requires-Dist: tensorboard==2.18.0
Requires-Dist: ultralytics==8.3.28
Requires-Dist: transformers==4.44.2
Requires-Dist: colorcet==3.1.0
